terrainman/__init__.py
terrainman/srtm.py
terrainman/tsi.py
terrainman/util.py
terrainman-0.0.38.dist-info/LICENSE
terrainman-0.0.38.dist-info/METADATA
terrainman-0.0.38.dist-info/WHEEL
terrainman-0.0.38.dist-info/RECORD
