Metadata-Version: 2.1
Name: terrainman
Version: 0.0.38
Summary: A package for downloading and managing high-fidelity terrain files and solar irradiance data
Author: Liam Robinson
Author-email: robin502@purdue.edu
Requires-Python: >3.8
Classifier: License :: OSI Approved :: GNU General Public License v3 (GPLv3)
Classifier: Operating System :: MacOS
Classifier: Programming Language :: Python :: 3
Classifier: Programming Language :: Python :: 3.9
Classifier: Programming Language :: Python :: 3.10
Classifier: Programming Language :: Python :: 3.11
Requires-Dist: bs4 (>=0.0.1)
Requires-Dist: netCDF4 (>=1.6.3)
Requires-Dist: numpy (>=1.24.2)
Requires-Dist: python-dotenv (>=1.0.0)
Requires-Dist: rasterio (>=1.3.6)
Requires-Dist: requests (>=2.26.0)
Requires-Dist: scipy (>=1.10.1)
Project-URL: Documentation, https://python-poetry.org/docs/
